wajp/__init__.py
wajp/py.typed
wajp-0.3.0.dist-info/WHEEL
wajp-0.3.0.dist-info/METADATA
wajp-0.3.0.dist-info/RECORD
